fluxpark/__init__.py
fluxpark/config/__init__.py
fluxpark/config/fluxpark_config.py
fluxpark/io/__init__.py
fluxpark/io/raster_tools.py
fluxpark/io/vector_tools.py
fluxpark/postprocessing/__init__.py
fluxpark/postprocessing/post_process.py
fluxpark/postprocessing/write_output.py
fluxpark/prepgrids/__init__.py
fluxpark/prepgrids/interpolation.py
fluxpark/prepgrids/prep_grids.py
fluxpark/setup/__init__.py
fluxpark/setup/core_initialization.py
fluxpark/submodels/__init__.py
fluxpark/submodels/etref.py
fluxpark/submodels/interception.py
fluxpark/submodels/rootwateruptake.py
fluxpark/submodels/soilevaporation.py
fluxpark/utils/__init__.py
fluxpark/utils/common.py
fluxpark/workflow/__init__.py
fluxpark/workflow/loopstate.py
fluxpark/workflow/runner.py
fluxpark-0.1.6.dist-info/licenses/LICENSE.txt
fluxpark-0.1.6.dist-info/METADATA
fluxpark-0.1.6.dist-info/WHEEL
fluxpark-0.1.6.dist-info/top_level.txt
fluxpark-0.1.6.dist-info/RECORD
