Metadata-Version: 2.4
Name: fluxpark
Version: 0.1.6
Summary: Spatially-explicit hydrological model for simulating evaporation fluxes and groundwater recharge
Author-email: Bernard Voortman <bernard.voortman@moisture-matters.nl>
License: FluxPark Custom License v1.0
Project-URL: Homepage, https://github.com/Moisture-Matters/fluxpark
Project-URL: Source, https://github.com/Moisture-Matters/fluxpark
Project-URL: Bug Tracker, https://github.com/Moisture-Matters/fluxpark/issues
Classifier: Development Status :: 4 - Beta
Classifier: Intended Audience :: Science/Research
Classifier: License :: Other/Proprietary License
Classifier: Programming Language :: Python :: 3
Classifier: Programming Language :: Python :: 3.9
Classifier: Topic :: Scientific/Engineering :: Hydrology
Requires-Python: >=3.9
License-File: LICENSE.txt
Requires-Dist: numpy>=1.23.4
Requires-Dist: pandas>=1.5.1
Requires-Dist: scipy>=1.9.2
Requires-Dist: openpyxl>=3.0.0
Provides-Extra: test
Requires-Dist: pytest>=7.0; extra == "test"
Requires-Dist: pytest-cov; extra == "test"
Requires-Dist: flake8; extra == "test"
Provides-Extra: docs
Requires-Dist: sphinx; extra == "docs"
Requires-Dist: sphinx-rtd-theme; extra == "docs"
Dynamic: license-file
